ggm/__init__.py
ggm/app/__init__.py
ggm/app/http_api.py
ggm/app/mqtt_bridge.py
ggm/app/rpi_health.py
ggm/client/__init__.py
ggm/client/auth.py
ggm/client/stream_client.py
ggm/client/sync_client.py
ggm/core/__init__.py
ggm/core/data_kernel.py
ggm/core/ironbase.py
ggm/core/resource_manager.py
ggm/core/resource_worker.py
ggm/core/state_updater.py
ggm/core/uplink.py
ggm/distfiles/client.json
ggm/distfiles/client_config.json
ggm/distfiles/full.json
ggm/distfiles/gateway.json
ggm/distfiles/ggm@.service
ggm/distfiles/mqtt.dist
ggm/distfiles/paths.json
ggm/distfiles/server.json
ggm/distfiles/timescaledb.dist
ggm/lib/__init__.py
ggm/lib/aiomqtthelper.py
ggm/lib/auth.py
ggm/lib/data.py
ggm/lib/heart.py
ggm/lib/kernel.py
ggm/lib/kontext.py
ggm/lib/logging.py
ggm/lib/sync_context.py
ggm/lib/utils.py
ggm/storage/__init__.py
ggm/storage/jsqlite.py
ggm/storage/nostorage.py
ggm/storage/ssqlite.py
ggm/storage/timescale.py
gilgamesh-0.100.0.data/scripts/gilgamesh
gilgamesh-0.100.0.dist-info/LICENSE
gilgamesh-0.100.0.dist-info/METADATA
gilgamesh-0.100.0.dist-info/WHEEL
gilgamesh-0.100.0.dist-info/top_level.txt
gilgamesh-0.100.0.dist-info/RECORD
