Metadata-Version: 2.1
Name: gilgamesh
Version: 0.100.0
Summary: distributed data
Home-page: https://gitlab.com/gilgamesh-zmq/ggm
Author: Leonard Pollak
Author-email: leonardp@tr-host.de
License: AGPL-3.0-or-later
Keywords: beta data
Platform: UNKNOWN
Classifier: Development Status :: 4 - Beta
Classifier: Topic :: Utilities
Classifier: Topic :: System :: Distributed Computing
Classifier: License :: OSI Approved :: GNU Affero General Public License v3 or later (AGPLv3+)
Classifier: Programming Language :: Python :: 3.7
Requires-Python: >=3.7
Requires-Dist: pyzmq
Requires-Dist: aiohttp
Requires-Dist: blosc
Requires-Dist: ujson
Provides-Extra: mqtt
Requires-Dist: paho-mqtt ; extra == 'mqtt'
Provides-Extra: timescaledb
Requires-Dist: psycopg2 ; extra == 'timescaledb'
